wood_nano/wood_nano_ext.abi3.so
wood_nano/__init__.py
wood_nano/conversions_python.py
wood_nano-0.3.5.dist-info/RECORD
wood_nano-0.3.5.dist-info/WHEEL
wood_nano-0.3.5.dist-info/METADATA
wood_nano-0.3.5.dist-info/licenses/LICENSE
