Metadata-Version: 2.1
Name: wood_nano
Version: 0.3.5
Summary: Binding for wood project that is compiled into a binding using nanobind and scikit-build
Author-Email: Petras Vestartas <petrasvestartas@gmail.com>
Classifier: License :: OSI Approved :: BSD License
Project-URL: Homepage, https://github.com/petrasvestartas/wood_nano
Requires-Python: >=3.9
